<?xml version="1.0" encoding="utf-8"?>
<Backup>
  <Driver>
    <IDDriver>1</IDDriver>
    <DriverName>Marko</DriverName>
    <DriverSurname>Markovic</DriverSurname>
    <Telephone>1576489</Telephone>
    <LicenceNumber>465</LicenceNumber>
  </Driver>
  <Driver>
    <IDDriver>2</IDDriver>
    <DriverName>Ivan</DriverName>
    <DriverSurname>Ivanovic</DriverSurname>
    <Telephone>7946813</Telephone>
    <LicenceNumber>114456791</LicenceNumber>
  </Driver>
  <Driver>
    <IDDriver>3</IDDriver>
    <DriverName>Marko</DriverName>
    <DriverSurname>Markovic</DriverSurname>
    <Telephone>91734658</Telephone>
    <LicenceNumber>753159</LicenceNumber>
  </Driver>
  <Car>
    <IDCar>1</IDCar>
    <CarType>Covertible</CarType>
    <Brand>VW</Brand>
    <YearOfMaking>2000</YearOfMaking>
    <Mileage>200000</Mileage>
    <CarReserved>True</CarReserved>
  </Car>
  <Car>
    <IDCar>2</IDCar>
    <CarType>Van</CarType>
    <Brand>Mercedes</Brand>
    <YearOfMaking>2011</YearOfMaking>
    <Mileage>100000</Mileage>
    <CarReserved>False</CarReserved>
  </Car>
  <Car>
    <IDCar>3</IDCar>
    <CarType>Sedan</CarType>
    <Brand>BMW</Brand>
    <YearOfMaking>2010</YearOfMaking>
    <Mileage>200000</Mileage>
    <CarReserved>False</CarReserved>
  </Car>
  <Car>
    <IDCar>4</IDCar>
    <CarType>Coupe</CarType>
    <Brand>Alfa Romeo</Brand>
    <YearOfMaking>2018</YearOfMaking>
    <Mileage>270000</Mileage>
    <CarReserved>False</CarReserved>
  </Car>
  <Car>
    <IDCar>5</IDCar>
    <CarType>Limousine</CarType>
    <Brand>Ford</Brand>
    <YearOfMaking>2015</YearOfMaking>
    <Mileage>150000</Mileage>
    <CarReserved>True</CarReserved>
  </Car>
  <TravelInfo>
    <IDTravelInfo>1</IDTravelInfo>
    <Status>Active</Status>
    <DriverID>1</DriverID>
    <TravelLength>100</TravelLength>
    <DaysExpected>3</DaysExpected>
    <StartCity>2</StartCity>
    <StopCity>3</StopCity>
    <CarID>1</CarID>
  </TravelInfo>
  <TravelInfo>
    <IDTravelInfo>2</IDTravelInfo>
    <Status>Future</Status>
    <DriverID>2</DriverID>
    <TravelLength>500</TravelLength>
    <DaysExpected>5</DaysExpected>
    <StartCity>2</StartCity>
    <StopCity>4</StopCity>
    <CarID>2</CarID>
  </TravelInfo>
  <TravelInfo>
    <IDTravelInfo>3</IDTravelInfo>
    <Status>Future</Status>
    <DriverID>3</DriverID>
    <TravelLength>1100</TravelLength>
    <DaysExpected>15</DaysExpected>
    <StartCity>2</StartCity>
    <StopCity>3</StopCity>
    <CarID>3</CarID>
  </TravelInfo>
  <Route>
    <IDRoute>3</IDRoute>
    <Time>10:00</Time>
    <CoordinatesALength>45.789</CoordinatesALength>
    <CoordinatesAWidth>78.987</CoordinatesAWidth>
    <CoordinatesBLength>78.195431</CoordinatesBLength>
    <CoordinatesBWidth>12.444</CoordinatesBWidth>
    <TravelLength>232</TravelLength>
    <AverageSpeed>200</AverageSpeed>
    <FuelConsumption>14</FuelConsumption>
    <TravelInfoID>3</TravelInfoID>
  </Route>
  <Route>
    <IDRoute>5</IDRoute>
    <Time>10:00</Time>
    <CoordinatesALength>45.789</CoordinatesALength>
    <CoordinatesAWidth>78.987</CoordinatesAWidth>
    <CoordinatesBLength>78.195431</CoordinatesBLength>
    <CoordinatesBWidth>12.444</CoordinatesBWidth>
    <TravelLength>232</TravelLength>
    <AverageSpeed>200</AverageSpeed>
    <FuelConsumption>14</FuelConsumption>
    <TravelInfoID>1</TravelInfoID>
  </Route>
  <Route>
    <IDRoute>6</IDRoute>
    <Time>10:00</Time>
    <CoordinatesALength>45.789</CoordinatesALength>
    <CoordinatesAWidth>45</CoordinatesAWidth>
    <CoordinatesBLength>341</CoordinatesBLength>
    <CoordinatesBWidth>12</CoordinatesBWidth>
    <TravelLength>23</TravelLength>
    <AverageSpeed>144</AverageSpeed>
    <FuelConsumption>12</FuelConsumption>
    <TravelInfoID>2</TravelInfoID>
  </Route>
</Backup>